markov_chain_attribution/MarkovChainBigQuery.py
markov_chain_attribution/MarkovChainGoogleAnalytics.py
markov_chain_attribution/__init__.py
markov_chain_attribution/routes.py
markov_chain_attribution/run.py
tests/__init__.py
markov_chain_attribution-0.1.0.dev1.dist-info/METADATA
markov_chain_attribution-0.1.0.dev1.dist-info/WHEEL
markov_chain_attribution-0.1.0.dev1.dist-info/top_level.txt
markov_chain_attribution-0.1.0.dev1.dist-info/RECORD
