Metadata-Version: 2.1
Name: markov-chain-attribution
Version: 0.1.0.dev1
Summary: Digital Market Attribution
Home-page: https://github.com/ritikjain51/markov-chain-attribution
Author: Ritik Jain
License: Apache 2.0
Download-URL: https://github.com/ritikjain51/markov-chain-attribution/releases/tag/v0.1.0.dev1
Keywords: markov-chain-attribution markov attribution monte carlo
Platform: UNKNOWN
Classifier: Development Status :: 3 - Alpha
Classifier: Topic :: Office/Business :: Financial
Classifier: Natural Language :: English
Classifier: Operating System :: OS Independent
Classifier: License :: OSI Approved :: Apache Software License
Classifier: Programming Language :: Python :: 3
Classifier: Programming Language :: Python :: 3.6
Classifier: Programming Language :: Python :: 3.7
Classifier: Programming Language :: Python :: 3.8
Requires-Python: >=3.6.0
Requires-Dist: pandas (>=1.0.2)
Requires-Dist: numpy (>=1.18.2)
